sbijax/__init__.py
sbijax/_src/__init__.py
sbijax/_src/_ne_base.py
sbijax/_src/_sbi_base.py
sbijax/_src/cmpe.py
sbijax/_src/cmpe_test.py
sbijax/_src/conftest.py
sbijax/_src/fmpe.py
sbijax/_src/fmpe_test.py
sbijax/_src/nass.py
sbijax/_src/nass_test.py
sbijax/_src/nasss.py
sbijax/_src/nasss_test.py
sbijax/_src/nle.py
sbijax/_src/nle_test.py
sbijax/_src/npe.py
sbijax/_src/npe_test.py
sbijax/_src/nre.py
sbijax/_src/nre_test.py
sbijax/_src/snle.py
sbijax/_src/abc/__init__.py
sbijax/_src/abc/smc_abc.py
sbijax/_src/abc/smc_abc_test.py
sbijax/_src/experimental/__init__.py
sbijax/_src/experimental/aio.py
sbijax/_src/experimental/aio_test.py
sbijax/_src/experimental/npse.py
sbijax/_src/experimental/npse_test.py
sbijax/_src/experimental/nn/__init__.py
sbijax/_src/experimental/nn/make_score_network.py
sbijax/_src/experimental/nn/make_simformer.py
sbijax/_src/mcmc/__init__.py
sbijax/_src/mcmc/conftest.py
sbijax/_src/mcmc/irmh.py
sbijax/_src/mcmc/irmh_test.py
sbijax/_src/mcmc/mala.py
sbijax/_src/mcmc/mala_test.py
sbijax/_src/mcmc/nuts.py
sbijax/_src/mcmc/nuts_test.py
sbijax/_src/mcmc/rmh.py
sbijax/_src/mcmc/rmh_test.py
sbijax/_src/mcmc/slice.py
sbijax/_src/mcmc/slice_test.py
sbijax/_src/mcmc/util.py
sbijax/_src/nn/__init__.py
sbijax/_src/nn/make_consistency_model.py
sbijax/_src/nn/make_continuous_flow.py
sbijax/_src/nn/make_flow.py
sbijax/_src/nn/make_mdn.py
sbijax/_src/nn/make_mlp.py
sbijax/_src/nn/make_nass_network.py
sbijax/_src/nn/make_resnet.py
sbijax/_src/nn/nass_net.py
sbijax/_src/nn/nasss_net.py
sbijax/_src/plot/__init__.py
sbijax/_src/plot/plot.py
sbijax/_src/plot/styles/sbijax-bluish.mplstyle
sbijax/_src/plot/styles/sbijax-grayish.mplstyle
sbijax/_src/plot/styles/sbijax.mplstyle
sbijax/_src/util/__init__.py
sbijax/_src/util/data.py
sbijax/_src/util/data_test.py
sbijax/_src/util/dataloader.py
sbijax/_src/util/early_stopping.py
sbijax/_src/util/train_state.py
sbijax/_src/util/types.py
sbijax/experimental/__init__.py
sbijax/experimental/nn/__init__.py
sbijax-0.3.4.dist-info/METADATA
sbijax-0.3.4.dist-info/WHEEL
sbijax-0.3.4.dist-info/licenses/LICENSE
sbijax-0.3.4.dist-info/RECORD
