Metadata-Version: 2.4
Name: sbijax
Version: 0.3.4
Summary:  Simulation-based inference in JAX
Project-URL: Homepage, https://github.com/dirmeier/sbijax
Project-URL: Documentation, https://sbijax.readthedocs.io
Author-email: Simon Dirmeier <sfyrbnd@pm.me>
License-Expression: Apache-2.0
License-File: LICENSE
Keywords: abc,approximate Bayesian computation,sbi,simulation-based inference
Classifier: Development Status :: 4 - Beta
Classifier: Intended Audience :: Science/Research
Classifier: License :: OSI Approved :: Apache Software License
Classifier: Programming Language :: Python :: 3
Classifier: Programming Language :: Python :: 3.10
Classifier: Programming Language :: Python :: 3.11
Classifier: Programming Language :: Python :: 3.12
Requires-Python: >=3.9
Requires-Dist: arviz>=0.17.1
Requires-Dist: blackjax-nightly>=1.0.0.post17
Requires-Dist: diffrax>=0.6.1
Requires-Dist: dm-haiku>=0.0.9
Requires-Dist: einops>=0.8.0
Requires-Dist: matplotlib>=3.6.2
Requires-Dist: optax>=0.1.3
Requires-Dist: seaborn>=0.12.2
Requires-Dist: surjectors>=0.3.3
Requires-Dist: tensorflow-datasets>=4.9.3
Requires-Dist: tensorflow>=2.15.0
Requires-Dist: tfp-nightly>=0.20.0.dev20230404
Requires-Dist: tqdm>=4.64.1
Provides-Extra: examples
Requires-Dist: jrnmm==0.1.1.post2; extra == 'examples'
